{
  "model": "ruthwell.nxz",
  "annotations": [
    {
      "name": 100,
      "type": "point",
      "position": [
        -6.27,
        3487.99,
        179.55
      ],
      "radius": "100",
      "view": [
        0,
        0,
        -118.16883087158203,
        2610.291259765625,
        29.743642807006836,
        9305.624795169471
      ]
    },
    {
      "name": 101,
      "type": "point",
      "position": [
        478.95,
        4875.01,
        151.58
      ],
      "radius": "100",
      "view": [
        62.79617434633827,
        62.33780811023361,
        -118.16883087158203,
        2610.291259765625,
        29.743642807006836,
        6783.800475678545
      ]
    },
    {
      "name": 102,
      "type": "point",
      "position": [
        -15.34,
        3430.1,
        -119.01
      ],
      "radius": "100",
      "view": [
        -183.23190288283675,
        3.552338329811136,
        -118.16883087158203,
        2610.291259765625,
        29.743642807006836,
        3926.051592660046
      ]
    },
    {
      "name": 103,
      "type": "point",
      "position": [
        4.98,
        4790.9,
        -67
      ],
      "radius": "100",
      "view": [
        -181.85680417452375,
        40.954812736801486,
        -118.16883087158203,
        2610.291259765625,
        29.743642807006836,
        8003.380350242647
      ]
    },
    {
      "name": 104,
      "type": "point",
      "position": [
        -262.57,
        2014.18,
        -1.71
      ],
      "radius": "100",
      "view": [
        -90.06896539456625,
        6.348161910899734,
        -118.16883087158203,
        2610.291259765625,
        29.743642807006836,
        8003.380350242647
      ]
    }
  ],
  "nextID": 105
}